{
    "name": " bynow's Cracked AppStore",
    "message": "发布/收录请联系:\r\nQQ：3024173773（备注CrackAPP）\r\n若出现下载无速度请使用代理，或者加入QQ群（130037168）从群文件获取，源中软件均来自网络",
    "identifier": "https://github.com/abcp3/CrackedApp/appstore.json",
    "sourceURL": "https://github.com/abcp3/CrackedApp/appstore.json",
    "sourceicon": "https://github.com/abcp3/CrackedApp/source.png",
    "payURL": "",
    "unlockURL": "https://github.com/abcp3/CrackedApp/appstore.json",
    "apps": [
        {
            "name": "DJ多多",
            "version": "3.7",
            "versionDate": "2021-02-02",
            "versionDescription": "作者：全能签\n描述：一款手机端的ipa签名工具，导入P12证书以及安装包即可签名，可本地直接安装ipa包。更新一键恢复证书!兑换输入8888导入企业证书",
            "lock": "0",
            "downloadURL": "https://share.initnil.com/iOS-Patched-IPAs/Crack/DJ多多Crack.ipa",
            "isLanZouCloud": "0",
            "iconURL": "https://qnq.nuosike.cn/uploads/20200920/110fa335493e1bb6d157a954952c0a69.png",
            "tintColor": "018084",
        },
        {
            "name": "酷我音乐",
            "version": "1.2.6",
            "versionDate": "2022-03-02",
            "versionDescription": "作者：bynow\n描述：酷我音乐VIP，无损音质畅听下载",
            "lock": "0",
            "downloadURL": "https://share.initnil.com/iOS-Patched-IPAs/Crack/酷我音乐Crack.ipa",
            "isLanZouCloud": "0",
            "iconURL": "https://topstore.vip/image/323222878.png",
            "tintColor": "",
            "size": ""
        }
    ]
}
